polyan/__init__.py
polyan/polyan.py
polyan/Data/GRCh38.csv
polyan/Data/Untitled.ipynb
polyan/Data/__init__.py
polyan/Data/parameters.json
polyan/Data/sacCer3.csv
polyan-2022.1.0.dist-info/LICENSE
polyan-2022.1.0.dist-info/METADATA
polyan-2022.1.0.dist-info/WHEEL
polyan-2022.1.0.dist-info/top_level.txt
polyan-2022.1.0.dist-info/RECORD
