Metadata-Version: 2.1
Name: polyan
Version: 2022.1.0
Summary: A package for simulating polysome profiles from Ribo-Seq data
Home-page: https://github.com/tobiasvonderhaar/polyan
Author: Tobias von der Haar, Fabio de Lima Hedayioglu
Author-email: T.von-der-Haar@kent.ac.uk
License: MIT
Platform: UNKNOWN
Classifier: Programming Language :: Python :: 3
Classifier: License :: OSI Approved :: MIT License
Classifier: Operating System :: OS Independent
Classifier: Development Status :: 3 - Alpha
Classifier: Framework :: Jupyter
Classifier: Framework :: Matplotlib
Classifier: Intended Audience :: Science/Research
Classifier: License :: OSI Approved :: MIT License
Classifier: Topic :: Scientific/Engineering :: Bio-Informatics
Classifier: Topic :: Scientific/Engineering :: Visualization
Requires-Python: >=3.6
Requires-Dist: pandas
Requires-Dist: numpy
Requires-Dist: matplotlib
Requires-Dist: scipy
